cvplus/_version.py
cvplus/cli/imgconv.py
cvplus/cv2keycode.py
cvplus/cvt.py
cvplus/display.py
cvplus/draw.py
cvplus/gui/camera_capture.py
cvplus/gui/color_range_selector.py
cvplus/shape.py
cvplus/utils/__init__.py
cvplus/utils/color_range.py
cvplus/utils/image_files.py
cvplus-0.1.4.dist-info/LICENSE
cvplus-0.1.4.dist-info/WHEEL
cvplus-0.1.4.dist-info/METADATA
cvplus-0.1.4.dist-info/RECORD
